ratsimulator/Agent.py
ratsimulator/__init__.py
ratsimulator/Environment/ABCEnvironment.py
ratsimulator/Environment/OpenField.py
ratsimulator/Environment/Rectangle.py
ratsimulator/Environment/Walls.py
ratsimulator/Environment/__init__.py
ratsimulator/Environment/methods.py
rat_simulator-1.2.0.dist-info/LICENSE
rat_simulator-1.2.0.dist-info/METADATA
rat_simulator-1.2.0.dist-info/WHEEL
rat_simulator-1.2.0.dist-info/top_level.txt
rat_simulator-1.2.0.dist-info/RECORD
