Metadata-Version: 2.1
Name: rat-simulator
Version: 1.2.0
Summary: A rat in an environment simulator
Home-page: https://github.com/Vemundss/rat-simulator
Author: Vemund S. Schoyen
Author-email: vemund@live.com
License: UNKNOWN
Platform: UNKNOWN
Classifier: Programming Language :: Python :: 3
Classifier: License :: OSI Approved :: MIT License
Classifier: Operating System :: OS Independent
License-File: LICENSE
Requires-Dist: scipy
Requires-Dist: numpy
